{
    "posts": [
        {
            "id": "32c6e0a3-0d66-817b-b02b-ea25327bc127",
            "title": "치즈가 태어났습니다 🐄",
            "summary": "1월 6일, 밀크가 새끼를 낳았습니다. 우리는 그 아이를 치즈라 불렀습니다. 같은 날, 요셉의 막내아들 생일이기도 했어요.",
            "content": "1월 6일. 밀크가 새끼를 낳았습니다.\n우리는 그 아이를 '치즈'라 불렀습니다.\n그날은 요셉의 막내아들 생일이기도 했습니다.\n\n치즈는 아직 작습니다. 귀가 크고, 눈이 맑습니다.\n무무목장도 그렇습니다. 이제 막 시작했습니다.\n\n킹스베리초지에서는 진짜 치즈도 만들기 시작했습니다.\n해발 1,000m 고원의 A2 저지 목초 치즈.\n이름이 운명이었나 봅니다 🧀",
            "videoUrl": "https://youtube.com/shorts/A4zxyXdr064?feature=share",
            "tags": [
                "#오늘의목장"
            ],
            "order": 1,
            "createdAt": "2026-03-23T12:58:00.000Z"
        },
        {
            "id": "32c6e0a3-0d66-8157-b5cd-de318dc57d86",
            "title": "오늘도 화이팅! 하이파이브!!",
            "summary": "A2 저지종은 사람을 친근하게 여기고 머리로 힘내라고 하이파이브를 해줍니다.",
            "content": "A2 저지종은 다른 소들과는 달리 사람을 참 친근하게 여겨요.\n가까이 다가오면 머리로 톡— 하고 '힘내!' 하이파이브를 해준답니다.\n\n오늘도 화이팅!",
            "videoUrl": "https://youtube.com/shorts/7GJfYZaj3TY?feature=share",
            "tags": [
                "#오늘의목장"
            ],
            "order": 2,
            "createdAt": "2026-03-23T13:22:00.000Z"
        },
        {
            "id": "32c6e0a3-0d66-819a-ab36-caacc8dc7b96",
            "title": "수줍은 치즈의 '킁킁'",
            "summary": "낯가리지만 호기심 많은 송아지 치즈가 조심스럽게 다가와 킁킁하며 인사합니다.",
            "content": "송아지 '치즈'는 아직 낯을 많이 가려요.\n처음 보는 사람은 멀찍이서 눈으로만 살피고,\n사슴처럼 뛰어 다니다가 조금만 소리가 나도 엄마 뒤로 쏙 숨곤 해요.\n\n그래도 호기심이 많아서요.\n손에 든 건 뭐인지, 무슨 냄새가 나는지 궁금해져서\n잠깐 멈춰 서 있다가… 수줍게 한 걸음, 또 한 걸음 다가와요.\n\n그리고는 코끝으로 '킁킁'—\n인사하듯 조심스럽게 냄새를 맡지요.",
            "videoUrl": "https://youtube.com/shorts/JU8Bkd2Kr1o",
            "tags": [
                "#오늘의목장"
            ],
            "order": 3,
            "createdAt": "2026-03-23T13:23:00.000Z"
        },
        {
            "id": "32a6e0a3-0d66-8115-ba79-c8797f5d2bf4",
            "title": "엄마와 치즈",
            "summary": "별이와 구름이의 평화로운 아침 목초지 산책",
            "content": "오늘 아침 목초지에 나가보니 별이랑 구름이가 나란히 풀을 뜯고 있었어요. 이슬 맺힌 풀밭 위를 천천히 걸어가는 모습이 정말 평화롭더라고요. 별이는 항상 구름이 옆에 딱 붙어서 다니는데, 둘이 자매처럼 사이가 좋아요. 목장 아침은 이렇게 고요하고 따뜻한 시간으로 시작됩니다.",
            "videoUrl": "https://youtube.com/shorts/x7fwgOMFFbM",
            "tags": [
                "#오늘의목장"
            ],
            "order": 5,
            "createdAt": "2026-03-21T06:57:00.000Z"
        }
    ],
    "lastSynced": "2026-03-25T16:59:00+09:00",
    "source": "notion-mcp-sync",
    "filter": "발행완료"
}